rubicon/objc/__init__.py
rubicon/objc/api.py
rubicon/objc/collections.py
rubicon/objc/ctypes_patch.py
rubicon/objc/eventloop.py
rubicon/objc/runtime.py
rubicon/objc/types.py
rubicon_objc-0.4.9.dist-info/LICENSE
rubicon_objc-0.4.9.dist-info/METADATA
rubicon_objc-0.4.9.dist-info/WHEEL
rubicon_objc-0.4.9.dist-info/top_level.txt
rubicon_objc-0.4.9.dist-info/RECORD
