Metadata-Version: 2.1
Name: rubicon-objc
Version: 0.4.9
Summary: A bridge between an Objective C runtime environment and Python.
Author-email: Russell Keith-Magee <russell@keith-magee.com>
Maintainer-email: BeeWare Team <team@beeware.org>
License: New BSD
Project-URL: Homepage, https://beeware.org/rubicon
Project-URL: Funding, https://beeware.org/contributing/membership/
Project-URL: Documentation, https://rubicon-objc.readthedocs.io/en/latest/
Project-URL: Tracker, https://github.com/beeware/rubicon-objc/issues
Project-URL: Source, https://github.com/beeware/rubicon-objc
Keywords: macOS,iOS,Objective C
Classifier: Development Status :: 4 - Beta
Classifier: Intended Audience :: Developers
Classifier: License :: OSI Approved :: BSD License
Classifier: Programming Language :: Objective C
Classifier: Programming Language :: Python :: 3
Classifier: Programming Language :: Python :: 3.8
Classifier: Programming Language :: Python :: 3.9
Classifier: Programming Language :: Python :: 3.10
Classifier: Programming Language :: Python :: 3.11
Classifier: Programming Language :: Python :: 3.12
Classifier: Programming Language :: Python :: 3.13
Classifier: Programming Language :: Python :: 3 :: Only
Classifier: Topic :: Software Development
Requires-Python: >=3.8
License-File: LICENSE
Provides-Extra: dev
Requires-Dist: pre-commit==3.5.0; python_version < "3.9" and extra == "dev"
Requires-Dist: pre-commit==3.7.0; python_version >= "3.9" and extra == "dev"
Requires-Dist: pytest==8.2.0; extra == "dev"
Requires-Dist: pytest-tldr==0.2.5; extra == "dev"
Requires-Dist: setuptools_scm==8.0.4; extra == "dev"
Requires-Dist: tox==4.15.0; extra == "dev"
Provides-Extra: docs
Requires-Dist: furo==2024.4.27; extra == "docs"
Requires-Dist: pyenchant==3.2.2; extra == "docs"
Requires-Dist: sphinx==7.1.2; python_version < "3.9" and extra == "docs"
Requires-Dist: sphinx==7.3.7; python_version >= "3.9" and extra == "docs"
Requires-Dist: sphinx_tabs==3.4.5; extra == "docs"
Requires-Dist: sphinx-autobuild==2021.3.14; python_version < "3.9" and extra == "docs"
Requires-Dist: sphinx-autobuild==2024.4.16; python_version >= "3.9" and extra == "docs"
Requires-Dist: sphinx-copybutton==0.5.2; extra == "docs"
Requires-Dist: sphinxcontrib-spelling==8.0.0; extra == "docs"
